setup.py
py_validate/__init__.py
py_validate/api.py
py_validate.egg-info/PKG-INFO
py_validate.egg-info/SOURCES.txt
py_validate.egg-info/dependency_links.txt
py_validate.egg-info/top_level.txt
py_validate/backend/__init__.py
py_validate/backend/base.py
py_validate/backend/helpers.py
py_validate/backend/shortcuts.py
py_validate/tests/__init__.py
py_validate/tests/backend/__init__.py
py_validate/tests/backend/test_base.py
py_validate/tests/backend/test_helpers.py
py_validate/tests/backend/test_shortcuts.py
py_validate/tests/validator/__init__.py
py_validate/tests/validator/test_inputs.py
py_validate/tests/validator/test_outputs.py
py_validate/tests/validator/test_stacking.py